pypi_pkg_tut/__init__.py
pypi_pkg_tut/main.py
pypi_pkg_tut-0.3.dist-info/METADATA
pypi_pkg_tut-0.3.dist-info/WHEEL
pypi_pkg_tut-0.3.dist-info/entry_points.txt
pypi_pkg_tut-0.3.dist-info/top_level.txt
pypi_pkg_tut-0.3.dist-info/RECORD
