Metadata-Version: 2.1
Name: pypi-pkg-tut
Version: 0.3
Summary: UNKNOWN
License: UNKNOWN
Platform: UNKNOWN
